skquantum/__init__.py
skquantum/combinatorial/__init__.py
skquantum/combinatorial/weighted_maxcut.py
skquantum/core/__init__.py
skquantum/core/hamiltonian.py
skquantum/core/qaoa.py
skquantum/core/vqe.py
skquantum/machine_learning/__init__.py
skquantum/machine_learning/quantum_multilayer_perceptron.py
skquantum/search/__init__.py
skquantum/search/quantum_ksat_solver.py
scikit_quantum-0.0.6.dist-info/LICENSE
scikit_quantum-0.0.6.dist-info/METADATA
scikit_quantum-0.0.6.dist-info/WHEEL
scikit_quantum-0.0.6.dist-info/top_level.txt
scikit_quantum-0.0.6.dist-info/RECORD
